tgpt/__init__.py
tgpt/commandline_interface.py
tgpt/config_handler.py
tgpt/gpt_client.py
tgpt/image_handler.py
tgpt/main.py
tgpt-0.1.0.dist-info/LICENSE
tgpt-0.1.0.dist-info/METADATA
tgpt-0.1.0.dist-info/WHEEL
tgpt-0.1.0.dist-info/entry_points.txt
tgpt-0.1.0.dist-info/top_level.txt
tgpt-0.1.0.dist-info/RECORD
