Metadata-Version: 2.1
Name: tgpt
Version: 0.1.0
Summary: TGPT is a CLI interface to OpenAI's GPT models, bringing GPT to the Linux terminal and console
Home-page: https://github.com/indeedion/TGPT
Author: Magnus Jansson
Author-email: mengus00@gmail.com
Classifier: Development Status :: 3 - Alpha
Classifier: Intended Audience :: End Users/Desktop
Classifier: License :: OSI Approved :: GNU General Public License v3 (GPLv3)
Classifier: Programming Language :: Python :: 3
Classifier: Programming Language :: Python :: 3.6
Classifier: Programming Language :: Python :: 3.7
Classifier: Programming Language :: Python :: 3.8
Classifier: Programming Language :: Python :: 3.9
Requires-Python: >=3.6
License-File: LICENSE
Requires-Dist: requests
